{
  "name": "Hyper's Custom Theme",
  "description": "A custom black, red, and purple theme for Discord.",
  "authors": [
    {
      "name": "嫌われ者",
      "id": "742111919539748975"
    }
  ],
  "spec": 2,
  "semanticColors": {
    "HEADER_PRIMARY": ["#000000", "#550000", "#330033"],
    "HEADER_SECONDARY": ["#550000", "#550000", "#330033"],
    "TEXT_NORMAL": ["#2e3338", "#FF0000", "#FF33CC"],
    "TEXT_MUTED": ["#747f8d", "#440000", "#990099"],
    "TEXT_LINK": ["#000000", "#FF0000", "#FF33CC"],
    "INTERACTIVE_NORMAL": ["#4f5660", "#FF0000", "#FF33CC"],
    "INTERACTIVE_HOVER": ["#2e3338", "#800000", "#990066"],
    "INTERACTIVE_ACTIVE": ["#060607", "#FF0000", "#FF33CC"],
    "INTERACTIVE_MUTED": ["#c7ccd1", "#440000", "#990099"],
    "BACKGROUND_PRIMARY": ["#ffffff", "#550000", "#330033"],
    "BACKGROUND_SECONDARY": ["#f2f3f5", "#550000", "#330033"],
    "BACKGROUND_SECONDARY_ALT": ["#ebedef", "#550000", "#330033"],
    "BACKGROUND_TERTIARY": ["#e3e5e8", "#550000", "#330033"],
    "BACKGROUND_ACCENT": ["#747f8d", "#800000", "#990066"],
    "BACKGROUND_FLOATING": ["#FFFFFF", "#550000", "#330033"],
    "BACKGROUND_MOBILE_PRIMARY": ["#f8f9f9", "#550000", "#330033"],
    "BACKGROUND_MOBILE_SECONDARY": ["#ffffff", "#550000", "#330033"],
    "BACKGROUND_NESTED_FLOATING": ["#ffffff", "#550000", "#330033"],
    "BACKGROUND_MESSAGE_HOVER": ["#FFFFFF", "#660000", "#660066"],
    "BACKGROUND_MODIFIER_HOVER": ["hsla(214, 9.9%, 50.4%, 0.08)", "#660000", "#660066"],
    "BACKGROUND_MODIFIER_ACTIVE": ["hsla(214, 9.9%, 50.4%, 0.16)", "#800000", "#990066"],
    "BACKGROUND_MODIFIER_SELECTED": ["hsla(214, 9.9%, 50.4%, 0.24)", "#660000", "#660066"],
    "BACKGROUND_MODIFIER_ACCENT": ["hsla(240, 7.7%, 2.5%, 0.08)", "#800000", "#990066"],
    "SCROLLBAR_THIN_THUMB": ["hsla(217, 7.6%, 33.5%, 0.3)", "#880000", "#990099"],
    "SCROLLBAR_THIN_TRACK": ["hsla(0, 0%, 0%, 0)", "transparent", "transparent"],
    "SCROLLBAR_AUTO_THUMB": ["#cccccc", "#FF0000", "#FF33CC"],
    "SCROLLBAR_AUTO_TRACK": ["#f2f2f2", "#FF0000", "#FF33CC"],
    "CHANNELTEXTAREA_BACKGROUND": ["#ebedef", "#660000", "#660066"],
    "CHANNELS_DEFAULT": ["#6a7480", "#FF0000", "#FF33CC"],
    "TEXT_DANGER": ["#FFFFFF", "#660000", "#660066"],
    "KEYBOARD": ["#FFFFFF", "#660000", "#660066"]
  },
  "rawColors": {
    "PRIMARY_500": "#550000",
    "PRIMARY_100": "#060607",
    "PRIMARY_200": "#660000",
    "PRIMARY_300": "#880000",
    "PRIMARY_360": "#990000",
    "PRIMARY_400": "#AA0000",
    "PRIMARY_600": "#000055",
    "PRIMARY_630": "#110033",
    "PRIMARY_660": "#220066",
    "PRIMARY_700": "#330099",
    "PRIMARY_800": "#4400CC",
    "BRAND_260": "#000033",
    "BRAND_360": "#330066",
    "BRAND_500": "#660099",
    "BRAND_560": "#8800CC",
    "YELLOW_300": "#9900FF",
    "GREEN_600": "#CC00FF",
    "RED_400": "#FF00FF",
    "WHITE_500": "#FFFFFF",
    "GREEN_360": "#00FF00",
    "PLUM_1": "#003300",
    "PLUM_3": "#004400",
    "PLUM_6": "#006600",
    "PLUM_9": "#CCCCCC",
    "PLUM_10": "#CCCCCC",
    "PLUM_11": "#CCCCCC",
    "PLUM_13": "#CCCCCC",
    "PLUM_17": "#CCCCCC",
    "PLUM_18": "#CCCCCC",
    "PLUM_19": "#CCCCCC",
    "PLUM_20": "#CCCCCC",
    "PLUM_22": "#CCCCCC",
    "PRIMARY_DARK": "#747474",
    "PRIMARY_DARK_100": "#FFFFFF",
    "PRIMARY_DARK_200": "#FFFFFF",
    "PRIMARY_DARK_300": "#B6B6B6",
    "PRIMARY_DARK_360": "#C8C8C8",
    "PRIMARY_DARK_400": "#bebee3",
    "PRIMARY_DARK_500": "#697eab",
    "PRIMARY_DARK_600": "#111011",
    "PRIMARY_DARK_630": "#1a1b21",
    "PRIMARY_DARK_700": "#101010",
    "PRIMARY_DARK_800": "#151515",
    "BRAND_NEW": "#b9e9ff",
    "STATUS_RED": "#bfb9ff",
    "STATUS_GREEN_600": "#bfb9ff"
  },
  "unsafeColors": {
    "CHAT_GREY": "#111011"
  },
  "background": {
    "blur": 0.1,
    "url": "https://media.discordapp.net/attachments/836793351818706984/1011473596704636928/image0.jpg",
    "alpha": 1.0
  }
}
